setup.py
django_payment_webmoney.egg-info/PKG-INFO
django_payment_webmoney.egg-info/SOURCES.txt
django_payment_webmoney.egg-info/dependency_links.txt
django_payment_webmoney.egg-info/not-zip-safe
django_payment_webmoney.egg-info/top_level.txt
webmoney/__init__.py
webmoney/admin.py
webmoney/forms.py
webmoney/models.py
webmoney/signals.py
webmoney/urls.py
webmoney/views.py