Metadata-Version: 1.1
Name: django-payment-webmoney
Version: 0.3.0
Summary: WebMoney Merchant Interface support for Django.
Home-page: http://code.google.com/p/django-payment-webmoney/
Author: Ivan Fedorov
Author-email: oxyum@oxyum.ru
License: UNKNOWN
Platform: UNKNOWN
Classifier: Development Status :: 3 - Alpha
Classifier: Environment :: Web Environment
Classifier: Intended Audience :: Developers
Classifier: License :: OSI Approved :: MIT License
Classifier: Operating System :: OS Independent
Classifier: Programming Language :: Python
Classifier: Framework :: Django
